chipfoundry_cli/__init__.py
chipfoundry_cli/main.py
chipfoundry_cli/utils.py
chipfoundry_cli-1.3.0.dist-info/LICENSE
chipfoundry_cli-1.3.0.dist-info/METADATA
chipfoundry_cli-1.3.0.dist-info/WHEEL
chipfoundry_cli-1.3.0.dist-info/entry_points.txt
chipfoundry_cli-1.3.0.dist-info/RECORD
