Metadata-Version: 2.1
Name: chipfoundry-cli
Version: 1.3.0
Summary: CLI tool to automate ChipFoundry project submission to SFTP server
Home-page: https://chipfoundry.io
License: Apache-2.0
Author: ChipFoundry
Author-email: marwan.abbas@chipfoundry.io
Requires-Python: >=3.8.1,<4.0
Classifier: License :: OSI Approved :: Apache Software License
Classifier: Programming Language :: Python :: 3
Classifier: Programming Language :: Python :: 3.9
Classifier: Programming Language :: Python :: 3.10
Classifier: Programming Language :: Python :: 3.11
Classifier: Programming Language :: Python :: 3.12
Classifier: Programming Language :: Python :: 3.13
Requires-Dist: click (>=8.0.0,<9)
Requires-Dist: httpx (>=0.24.0,<1.0)
Requires-Dist: paramiko (>=3.0.0,<4)
Requires-Dist: rich (>=13,<14)
Requires-Dist: textual (>=0.40.0,<1)
Requires-Dist: toml (>=0.10,<1.0)
Project-URL: Repository, https://github.com/chipfoundry/cf-cli
